[{"name": "Bernd Leno","x": 13.169999999999998,"y": 38.69,"passes": [{"name": "Christoph Kramer","count": 2},{"name": "Giulio Donati","count": 2},{"name": "Javier Hernández Balcázar","count": 1},{"name": "Jonathan Tah","count": 7},{"name": "Karim Bellarabi","count": 2},{"name": "Kyriakos Papadopoulos","count": 2},{"name": "Sebastian Boenisch","count": 2},{"name": "Stefan Kießling","count": 1},{"name": "Ömer Toprak","count": 1}]},{"name": "Christoph Kramer","x": 63.056666666666665,"y": 36.086666666666666,"passes": [{"name": "Giulio Donati","count": 4},{"name": "Javier Hernández Balcázar","count": 2},{"name": "Jonathan Tah","count": 10},{"name": "Julian Brandt","count": 6},{"name": "Karim Bellarabi","count": 4},{"name": "Kyriakos Papadopoulos","count": 9},{"name": "Sebastian Boenisch","count": 12},{"name": "Stefan Kießling","count": 7},{"name": "Ömer Toprak","count": 5}]},{"name": "Giulio Donati","x": 71.1,"y": 72.4857142857143,"passes": [{"name": "Javier Hernández Balcázar","count": 2},{"name": "Jonathan Tah","count": 6},{"name": "Julian Brandt","count": 5},{"name": "Karim Bellarabi","count": 6},{"name": "Stefan Kießling","count": 11},{"name": "Ömer Toprak","count": 4}]},{"name": "Javier Hernández Balcázar","x": 67.2,"y": 31.20909090909091,"passes": [{"name": "Jonathan Tah","count": 2},{"name": "Julian Brandt","count": 5},{"name": "Karim Bellarabi","count": 2},{"name": "Kyriakos Papadopoulos","count": 2},{"name": "Sebastian Boenisch","count": 8},{"name": "Stefan Kießling","count": 4},{"name": "Ömer Toprak","count": 4}]},{"name": "Jonathan Tah","x": 43.65714285714286,"y": 56.707142857142856,"passes": [{"name": "Julian Brandt","count": 1},{"name": "Karim Bellarabi","count": 1},{"name": "Kyriakos Papadopoulos","count": 19},{"name": "Sebastian Boenisch","count": 2},{"name": "Ömer Toprak","count": 5}]},{"name": "Julian Brandt","x": 77.45263157894736,"y": 29.978947368421053,"passes": [{"name": "Karim Bellarabi","count": 2},{"name": "Kyriakos Papadopoulos","count": 1},{"name": "Sebastian Boenisch","count": 9},{"name": "Stefan Kießling","count": 6},{"name": "Ömer Toprak","count": 11}]},{"name": "Karim Bellarabi","x": 76.13333333333334,"y": 52.39166666666667,"passes": [{"name": "Kyriakos Papadopoulos","count": 1},{"name": "Sebastian Boenisch","count": 1},{"name": "Stefan Kießling","count": 2},{"name": "Ömer Toprak","count": 7}]},{"name": "Kyriakos Papadopoulos","x": 42.318518518518516,"y": 23.07777777777778,"passes": [{"name": "Sebastian Boenisch","count": 9},{"name": "Stefan Kießling","count": 2},{"name": "Ömer Toprak","count": 4}]},{"name": "Sebastian Boenisch","x": 64.828125,"y": 8.771875,"passes": [{"name": "Stefan Kießling","count": 4},{"name": "Ömer Toprak","count": 7}]},{"name": "Stefan Kießling","x": 81.65882352941176,"y": 46.688235294117646,"passes": [{"name": "Ömer Toprak","count": 3}]},{"name": "Ömer Toprak","x": 56.486666666666665,"y": 40.309999999999995,"passes": []}]