[{"name": "Aleksandar Ignjovski","x": 45.15,"y": 62.324999999999996,"passes": [{"name": "Carlos Augusto Zambrano Ochandarte","count": 2},{"name": "David Ángel Abraham","count": 1},{"name": "Haris Seferović","count": 1},{"name": "Lukáš Hrádecký","count": 2},{"name": "Makoto Hasebe","count": 9},{"name": "Marc Stendera","count": 2},{"name": "Slobodan Medojević","count": 3},{"name": "Stefan Aigner","count": 9}]},{"name": "Alexander Meier","x": 51.375,"y": 32.4,"passes": [{"name": "Bastian Oczipka","count": 5},{"name": "David Ángel Abraham","count": 2},{"name": "Haris Seferović","count": 1},{"name": "Lukáš Hrádecký","count": 6},{"name": "Makoto Hasebe","count": 5},{"name": "Marc Stendera","count": 2},{"name": "Slobodan Medojević","count": 3},{"name": "Stefan Aigner","count": 4}]},{"name": "Bastian Oczipka","x": 50.54117647058823,"y": 6.2,"passes": [{"name": "David Ángel Abraham","count": 3},{"name": "Haris Seferović","count": 9},{"name": "Lukáš Hrádecký","count": 1},{"name": "Marc Stendera","count": 5},{"name": "Slobodan Medojević","count": 3}]},{"name": "Carlos Augusto Zambrano Ochandarte","x": 29.49,"y": 52.0,"passes": [{"name": "David Ángel Abraham","count": 1},{"name": "Lukáš Hrádecký","count": 1},{"name": "Makoto Hasebe","count": 6},{"name": "Marc Stendera","count": 2},{"name": "Slobodan Medojević","count": 1},{"name": "Stefan Aigner","count": 4}]},{"name": "David Ángel Abraham","x": 23.700000000000003,"y": 24.25,"passes": [{"name": "Lukáš Hrádecký","count": 4},{"name": "Marc Stendera","count": 1},{"name": "Stefan Aigner","count": 1}]},{"name": "Haris Seferović","x": 58.9875,"y": 14.537500000000001,"passes": [{"name": "Lukáš Hrádecký","count": 4},{"name": "Marc Stendera","count": 7},{"name": "Slobodan Medojević","count": 1},{"name": "Stefan Aigner","count": 1}]},{"name": "Lukáš Hrádecký","x": 12.1,"y": 43.88260869565217,"passes": [{"name": "Makoto Hasebe","count": 8},{"name": "Marc Stendera","count": 1},{"name": "Stefan Aigner","count": 1}]},{"name": "Makoto Hasebe","x": 41.733333333333334,"y": 72.04074074074073,"passes": [{"name": "Marc Stendera","count": 3},{"name": "Stefan Aigner","count": 14}]},{"name": "Marc Stendera","x": 67.38,"y": 34.3,"passes": [{"name": "Slobodan Medojević","count": 2},{"name": "Stefan Aigner","count": 2}]},{"name": "Slobodan Medojević","x": 40.71666666666667,"y": 31.816666666666663,"passes": [{"name": "Stefan Aigner","count": 2}]},{"name": "Stefan Aigner","x": 60.044444444444444,"y": 69.02777777777777,"passes": []}]