[{"name": "Andrea Consigli","x": 13.5,"y": 38.983333333333334,"passes": [{"name": "Federico Peluso","count": 3},{"name": "Francesco Acerbi","count": 4},{"name": "Paolo Cannavaro","count": 4},{"name": "Simone Missiroli","count": 5},{"name": "Šime Vrsaljko","count": 4}]},{"name": "Antonio Floro Flores","x": 77.39999999999999,"y": 23.40833333333333,"passes": [{"name": "Domenico Berardi","count": 6},{"name": "Federico Peluso","count": 9},{"name": "Francesco Acerbi","count": 2},{"name": "Francesco Magnanelli","count": 3},{"name": "Gregoire Defrel","count": 4},{"name": "Joseph Alfred Duncan","count": 7},{"name": "Paolo Cannavaro","count": 1},{"name": "Simone Missiroli","count": 3}]},{"name": "Domenico Berardi","x": 79.0764705882353,"y": 63.14705882352941,"passes": [{"name": "Federico Peluso","count": 1},{"name": "Francesco Acerbi","count": 1},{"name": "Francesco Magnanelli","count": 4},{"name": "Gregoire Defrel","count": 6},{"name": "Paolo Cannavaro","count": 1},{"name": "Simone Missiroli","count": 10},{"name": "Šime Vrsaljko","count": 12}]},{"name": "Federico Peluso","x": 64.444,"y": 4.12,"passes": [{"name": "Francesco Acerbi","count": 8},{"name": "Francesco Magnanelli","count": 5},{"name": "Gregoire Defrel","count": 2},{"name": "Joseph Alfred Duncan","count": 12},{"name": "Paolo Cannavaro","count": 4},{"name": "Simone Missiroli","count": 2}]},{"name": "Francesco Acerbi","x": 44.044444444444444,"y": 23.283333333333335,"passes": [{"name": "Francesco Magnanelli","count": 6},{"name": "Gregoire Defrel","count": 1},{"name": "Joseph Alfred Duncan","count": 2},{"name": "Paolo Cannavaro","count": 4},{"name": "Simone Missiroli","count": 1},{"name": "Šime Vrsaljko","count": 1}]},{"name": "Francesco Magnanelli","x": 55.724,"y": 42.48,"passes": [{"name": "Gregoire Defrel","count": 5},{"name": "Joseph Alfred Duncan","count": 5},{"name": "Paolo Cannavaro","count": 2},{"name": "Simone Missiroli","count": 2},{"name": "Šime Vrsaljko","count": 9}]},{"name": "Gregoire Defrel","x": 68.99230769230769,"y": 40.4076923076923,"passes": [{"name": "Joseph Alfred Duncan","count": 5},{"name": "Paolo Cannavaro","count": 1},{"name": "Simone Missiroli","count": 5},{"name": "Šime Vrsaljko","count": 2}]},{"name": "Joseph Alfred Duncan","x": 72.26666666666667,"y": 18.833333333333332,"passes": [{"name": "Paolo Cannavaro","count": 3},{"name": "Simone Missiroli","count": 4},{"name": "Šime Vrsaljko","count": 2}]},{"name": "Paolo Cannavaro","x": 39.99,"y": 48.730000000000004,"passes": [{"name": "Simone Missiroli","count": 3},{"name": "Šime Vrsaljko","count": 11}]},{"name": "Simone Missiroli","x": 77.225,"y": 61.79,"passes": [{"name": "Šime Vrsaljko","count": 9}]}]