[{"name": "Allan Marques Loureiro","x": 67.38064516129033,"y": 59.71612903225807,"passes": [{"name": "Christian Maggio","count": 20},{"name": "Elseid Hysaj","count": 1},{"name": "Gonzalo Gerardo Higuaín","count": 4},{"name": "Lorenzo Insigne","count": 5},{"name": "Manolo Gabbiadini","count": 6},{"name": "Marek Hamšík","count": 3},{"name": "Mirko Valdifiori","count": 10},{"name": "Raúl Albiol i Tortajada","count": 12},{"name": "Vlad Iulian Chiricheș","count": 6}]},{"name": "Christian Maggio","x": 52.324999999999996,"y": 73.45357142857142,"passes": [{"name": "Gonzalo Gerardo Higuaín","count": 3},{"name": "José Manuel Reina Páez","count": 3},{"name": "Lorenzo Insigne","count": 2},{"name": "Manolo Gabbiadini","count": 3},{"name": "Marek Hamšík","count": 2},{"name": "Mirko Valdifiori","count": 11},{"name": "Raúl Albiol i Tortajada","count": 8},{"name": "Vlad Iulian Chiricheș","count": 5}]},{"name": "Elseid Hysaj","x": 59.46756756756757,"y": 7.905405405405405,"passes": [{"name": "Gonzalo Gerardo Higuaín","count": 2},{"name": "José Manuel Reina Páez","count": 5},{"name": "Lorenzo Insigne","count": 13},{"name": "Marek Hamšík","count": 26},{"name": "Mirko Valdifiori","count": 8},{"name": "Raúl Albiol i Tortajada","count": 9},{"name": "Vlad Iulian Chiricheș","count": 11}]},{"name": "Gonzalo Gerardo Higuaín","x": 73.83846153846153,"y": 35.97692307692308,"passes": [{"name": "José Manuel Reina Páez","count": 1},{"name": "Lorenzo Insigne","count": 1},{"name": "Manolo Gabbiadini","count": 7},{"name": "Marek Hamšík","count": 5},{"name": "Mirko Valdifiori","count": 6},{"name": "Raúl Albiol i Tortajada","count": 3},{"name": "Vlad Iulian Chiricheș","count": 1}]},{"name": "José Manuel Reina Páez","x": 9.205555555555556,"y": 39.03333333333333,"passes": [{"name": "Lorenzo Insigne","count": 2},{"name": "Manolo Gabbiadini","count": 1},{"name": "Mirko Valdifiori","count": 2},{"name": "Raúl Albiol i Tortajada","count": 5},{"name": "Vlad Iulian Chiricheș","count": 7}]},{"name": "Lorenzo Insigne","x": 70.78571428571429,"y": 33.542857142857144,"passes": [{"name": "Manolo Gabbiadini","count": 5},{"name": "Marek Hamšík","count": 14},{"name": "Mirko Valdifiori","count": 3},{"name": "Raúl Albiol i Tortajada","count": 3}]},{"name": "Manolo Gabbiadini","x": 73.58461538461539,"y": 50.607692307692304,"passes": [{"name": "Marek Hamšík","count": 4},{"name": "Mirko Valdifiori","count": 2},{"name": "Raúl Albiol i Tortajada","count": 2}]},{"name": "Marek Hamšík","x": 67.73589743589743,"y": 23.08205128205128,"passes": [{"name": "Mirko Valdifiori","count": 14},{"name": "Raúl Albiol i Tortajada","count": 8},{"name": "Vlad Iulian Chiricheș","count": 7}]},{"name": "Mirko Valdifiori","x": 60.57096774193548,"y": 45.68709677419355,"passes": [{"name": "Raúl Albiol i Tortajada","count": 5},{"name": "Vlad Iulian Chiricheș","count": 2}]},{"name": "Raúl Albiol i Tortajada","x": 42.14324324324324,"y": 49.6,"passes": [{"name": "Vlad Iulian Chiricheș","count": 6}]}]