[{"name": "Daniele Croce","x": 63.620000000000005,"y": 30.869999999999997,"passes": [{"name": "Leandro Daniel Paredes","count": 7},{"name": "Levan Mchedlidze","count": 3},{"name": "Lorenzo Ariaudo","count": 1},{"name": "Marcel Büchel","count": 6},{"name": "Marco Zambelli","count": 3},{"name": "Massimo Maccarone","count": 1},{"name": "Piotr Zieliński","count": 5},{"name": "Uroš Ćosić","count": 1}]},{"name": "Leandro Daniel Paredes","x": 50.65161290322581,"y": 39.8,"passes": [{"name": "Levan Mchedlidze","count": 4},{"name": "Lorenzo Ariaudo","count": 8},{"name": "Marcel Büchel","count": 7},{"name": "Marco Zambelli","count": 5},{"name": "Massimo Maccarone","count": 3},{"name": "Piotr Zieliński","count": 11},{"name": "Uroš Ćosić","count": 8},{"name": "Vincent Laurini","count": 6},{"name": "Łukasz Skorupski","count": 2}]},{"name": "Levan Mchedlidze","x": 61.48888888888889,"y": 52.266666666666666,"passes": [{"name": "Lorenzo Ariaudo","count": 1},{"name": "Marcel Büchel","count": 2},{"name": "Marco Zambelli","count": 2},{"name": "Massimo Maccarone","count": 1},{"name": "Piotr Zieliński","count": 7},{"name": "Uroš Ćosić","count": 1},{"name": "Vincent Laurini","count": 7},{"name": "Łukasz Skorupski","count": 1}]},{"name": "Lorenzo Ariaudo","x": 35.48823529411764,"y": 27.694117647058825,"passes": [{"name": "Marcel Büchel","count": 1},{"name": "Marco Zambelli","count": 5},{"name": "Massimo Maccarone","count": 1},{"name": "Piotr Zieliński","count": 1},{"name": "Uroš Ćosić","count": 6},{"name": "Vincent Laurini","count": 1},{"name": "Łukasz Skorupski","count": 3}]},{"name": "Marcel Büchel","x": 53.75555555555556,"y": 28.83888888888889,"passes": [{"name": "Marco Zambelli","count": 8},{"name": "Massimo Maccarone","count": 3},{"name": "Piotr Zieliński","count": 4},{"name": "Uroš Ćosić","count": 2},{"name": "Łukasz Skorupski","count": 3}]},{"name": "Marco Zambelli","x": 50.82105263157895,"y": 8.742105263157894,"passes": [{"name": "Massimo Maccarone","count": 7},{"name": "Uroš Ćosić","count": 2},{"name": "Łukasz Skorupski","count": 6}]},{"name": "Massimo Maccarone","x": 57.17,"y": 24.110000000000003,"passes": [{"name": "Piotr Zieliński","count": 2},{"name": "Uroš Ćosić","count": 1}]},{"name": "Piotr Zieliński","x": 47.88947368421052,"y": 55.531578947368416,"passes": [{"name": "Vincent Laurini","count": 15},{"name": "Łukasz Skorupski","count": 2}]},{"name": "Uroš Ćosić","x": 35.327777777777776,"y": 51.138888888888886,"passes": [{"name": "Vincent Laurini","count": 8},{"name": "Łukasz Skorupski","count": 3}]},{"name": "Vincent Laurini","x": 42.526923076923076,"y": 73.8923076923077,"passes": [{"name": "Łukasz Skorupski","count": 5}]},{"name": "Łukasz Skorupski","x": 11.386666666666665,"y": 41.3,"passes": []}]