[{"name": "Gonzalo Castro Randon","x": 67.85000000000001,"y": 24.429166666666664,"passes": [{"name": "Henrikh Mkhitaryan","count": 11},{"name": "Joo-Ho Park","count": 13},{"name": "Julian Weigl","count": 10},{"name": "Marco Reus","count": 4},{"name": "Mats Hummels","count": 6},{"name": "Pierre-Emerick Aubameyang","count": 5},{"name": "Sokratis Papastathopoulos","count": 2},{"name": "İlkay Gündoğan","count": 5}]},{"name": "Henrikh Mkhitaryan","x": 75.84545454545454,"y": 20.945454545454545,"passes": [{"name": "Joo-Ho Park","count": 20},{"name": "Julian Weigl","count": 1},{"name": "Marco Reus","count": 1},{"name": "Mats Hummels","count": 4},{"name": "Pierre-Emerick Aubameyang","count": 2},{"name": "Roman Bürki","count": 2},{"name": "Sokratis Papastathopoulos","count": 1},{"name": "İlkay Gündoğan","count": 6},{"name": "Łukasz Piszczek","count": 3}]},{"name": "Joo-Ho Park","x": 68.90487804878049,"y": 7.475609756097561,"passes": [{"name": "Julian Weigl","count": 12},{"name": "Mats Hummels","count": 18},{"name": "Pierre-Emerick Aubameyang","count": 3},{"name": "Roman Bürki","count": 2},{"name": "Sokratis Papastathopoulos","count": 1},{"name": "İlkay Gündoğan","count": 3}]},{"name": "Julian Weigl","x": 57.70263157894736,"y": 36.08421052631579,"passes": [{"name": "Marco Reus","count": 2},{"name": "Mats Hummels","count": 11},{"name": "Pierre-Emerick Aubameyang","count": 1},{"name": "Roman Bürki","count": 5},{"name": "Sokratis Papastathopoulos","count": 8},{"name": "İlkay Gündoğan","count": 11},{"name": "Łukasz Piszczek","count": 10}]},{"name": "Marco Reus","x": 72.64583333333333,"y": 62.2875,"passes": [{"name": "Mats Hummels","count": 2},{"name": "Pierre-Emerick Aubameyang","count": 3},{"name": "Sokratis Papastathopoulos","count": 2},{"name": "İlkay Gündoğan","count": 19},{"name": "Łukasz Piszczek","count": 17}]},{"name": "Mats Hummels","x": 45.16326530612245,"y": 25.136734693877553,"passes": [{"name": "Pierre-Emerick Aubameyang","count": 3},{"name": "Roman Bürki","count": 17},{"name": "Sokratis Papastathopoulos","count": 11},{"name": "İlkay Gündoğan","count": 11},{"name": "Łukasz Piszczek","count": 2}]},{"name": "Pierre-Emerick Aubameyang","x": 55.03333333333333,"y": 47.88333333333333,"passes": [{"name": "Roman Bürki","count": 5},{"name": "İlkay Gündoğan","count": 1},{"name": "Łukasz Piszczek","count": 5}]},{"name": "Roman Bürki","x": 15.404545454545454,"y": 40.449999999999996,"passes": [{"name": "Sokratis Papastathopoulos","count": 11},{"name": "İlkay Gündoğan","count": 2},{"name": "Łukasz Piszczek","count": 1}]},{"name": "Sokratis Papastathopoulos","x": 43.46363636363636,"y": 56.415151515151514,"passes": [{"name": "İlkay Gündoğan","count": 16},{"name": "Łukasz Piszczek","count": 12}]},{"name": "İlkay Gündoğan","x": 62.63777777777777,"y": 54.577777777777776,"passes": [{"name": "Łukasz Piszczek","count": 19}]}]