[{"name": "Alexander Milosevic","x": 41.61818181818182,"y": 26.636363636363637,"passes": [{"name": "Andre Hoffmann","count": 5},{"name": "Ceyhun Gülselam","count": 7},{"name": "Kenan Karaman","count": 1},{"name": "Miiko Martín Albornoz Inola","count": 4},{"name": "Ron-Robert Zieler","count": 2},{"name": "Salif Sané","count": 1}]},{"name": "Andre Hoffmann","x": 54.629629629629626,"y": 41.05185185185186,"passes": [{"name": "Artur Sobiech","count": 3},{"name": "Ceyhun Gülselam","count": 10},{"name": "Edgar Prib","count": 5},{"name": "Hiroki Sakai","count": 4},{"name": "Kenan Karaman","count": 6},{"name": "Miiko Martín Albornoz Inola","count": 7},{"name": "Salif Sané","count": 5},{"name": "Uffe Manich Bech","count": 4}]},{"name": "Artur Sobiech","x": 63.07142857142857,"y": 48.65714285714286,"passes": [{"name": "Edgar Prib","count": 7},{"name": "Miiko Martín Albornoz Inola","count": 1},{"name": "Ron-Robert Zieler","count": 1},{"name": "Salif Sané","count": 3}]},{"name": "Ceyhun Gülselam","x": 44.612500000000004,"y": 54.824999999999996,"passes": [{"name": "Edgar Prib","count": 5},{"name": "Hiroki Sakai","count": 11},{"name": "Kenan Karaman","count": 1},{"name": "Miiko Martín Albornoz Inola","count": 2},{"name": "Ron-Robert Zieler","count": 4},{"name": "Salif Sané","count": 5},{"name": "Uffe Manich Bech","count": 2}]},{"name": "Edgar Prib","x": 73.64117647058823,"y": 43.076470588235296,"passes": [{"name": "Hiroki Sakai","count": 5},{"name": "Kenan Karaman","count": 3},{"name": "Salif Sané","count": 5},{"name": "Uffe Manich Bech","count": 9}]},{"name": "Hiroki Sakai","x": 50.24545454545455,"y": 75.7909090909091,"passes": [{"name": "Ron-Robert Zieler","count": 2},{"name": "Salif Sané","count": 4},{"name": "Uffe Manich Bech","count": 10}]},{"name": "Kenan Karaman","x": 76.6923076923077,"y": 17.46153846153846,"passes": [{"name": "Miiko Martín Albornoz Inola","count": 5},{"name": "Ron-Robert Zieler","count": 1},{"name": "Salif Sané","count": 6},{"name": "Uffe Manich Bech","count": 1}]},{"name": "Miiko Martín Albornoz Inola","x": 45.291666666666664,"y": 11.241666666666667,"passes": [{"name": "Ron-Robert Zieler","count": 5},{"name": "Salif Sané","count": 3}]},{"name": "Ron-Robert Zieler","x": 14.34,"y": 35.54,"passes": [{"name": "Salif Sané","count": 1}]},{"name": "Salif Sané","x": 68.56923076923077,"y": 36.90769230769231,"passes": [{"name": "Uffe Manich Bech","count": 1}]}]