[{"name": "Adalberto Peñaranda Maestre","x": 78.39999999999999,"y": 53.4,"passes": [{"name": "Cristiano Biraghi","count": 2},{"name": "Dimitri Foulquier","count": 3},{"name": "Francisco Manuel Rico Castro","count": 5},{"name": "Isaac Ajayi Success","count": 4},{"name": "Ricardo Miguel Moreira da Costa","count": 2},{"name": "Rubén Rochina Naixes","count": 4},{"name": "Rubén Salvador Pérez Del Mármol","count": 6},{"name": "Youssef El-Arabi","count": 3}]},{"name": "Andrés Eduardo Fernández Moreno","x": 11.450000000000001,"y": 36.792857142857144,"passes": [{"name": "Cristiano Biraghi","count": 2},{"name": "David Rodríguez Lombán","count": 4},{"name": "Dimitri Foulquier","count": 1},{"name": "Francisco Manuel Rico Castro","count": 2},{"name": "Isaac Ajayi Success","count": 4},{"name": "Ricardo Miguel Moreira da Costa","count": 6},{"name": "Rubén Rochina Naixes","count": 2},{"name": "Rubén Salvador Pérez Del Mármol","count": 1},{"name": "Youssef El-Arabi","count": 1}]},{"name": "Cristiano Biraghi","x": 53.317241379310346,"y": 8.451724137931034,"passes": [{"name": "David Rodríguez Lombán","count": 2},{"name": "Dimitri Foulquier","count": 1},{"name": "Francisco Manuel Rico Castro","count": 5},{"name": "Isaac Ajayi Success","count": 5},{"name": "Ricardo Miguel Moreira da Costa","count": 9},{"name": "Rubén Rochina Naixes","count": 9},{"name": "Rubén Salvador Pérez Del Mármol","count": 5},{"name": "Youssef El-Arabi","count": 2}]},{"name": "David Rodríguez Lombán","x": 40.107142857142854,"y": 52.25714285714286,"passes": [{"name": "Dimitri Foulquier","count": 4},{"name": "Francisco Manuel Rico Castro","count": 3},{"name": "Isaac Ajayi Success","count": 2},{"name": "Ricardo Miguel Moreira da Costa","count": 6},{"name": "Rubén Rochina Naixes","count": 1},{"name": "Rubén Salvador Pérez Del Mármol","count": 2}]},{"name": "Dimitri Foulquier","x": 55.36578947368421,"y": 73.23421052631579,"passes": [{"name": "Francisco Manuel Rico Castro","count": 15},{"name": "Isaac Ajayi Success","count": 7},{"name": "Ricardo Miguel Moreira da Costa","count": 4},{"name": "Rubén Rochina Naixes","count": 15},{"name": "Rubén Salvador Pérez Del Mármol","count": 2},{"name": "Youssef El-Arabi","count": 5}]},{"name": "Francisco Manuel Rico Castro","x": 70.71153846153847,"y": 43.315384615384616,"passes": [{"name": "Isaac Ajayi Success","count": 8},{"name": "Ricardo Miguel Moreira da Costa","count": 3},{"name": "Rubén Rochina Naixes","count": 5},{"name": "Rubén Salvador Pérez Del Mármol","count": 6},{"name": "Youssef El-Arabi","count": 5}]},{"name": "Isaac Ajayi Success","x": 80.24545454545455,"y": 40.40909090909091,"passes": [{"name": "Ricardo Miguel Moreira da Costa","count": 1},{"name": "Rubén Rochina Naixes","count": 5},{"name": "Rubén Salvador Pérez Del Mármol","count": 2}]},{"name": "Ricardo Miguel Moreira da Costa","x": 35.64090909090909,"y": 31.072727272727274,"passes": [{"name": "Rubén Rochina Naixes","count": 10},{"name": "Rubén Salvador Pérez Del Mármol","count": 5}]},{"name": "Rubén Rochina Naixes","x": 58.903703703703705,"y": 48.181481481481484,"passes": [{"name": "Rubén Salvador Pérez Del Mármol","count": 11},{"name": "Youssef El-Arabi","count": 10}]}]