[{"name": "Adriano Correia Claro","x": 71.14533333333333,"y": 8.030666666666667,"passes": [{"name": "Aleix Vidal Parreu","count": 1},{"name": "Arda Turan","count": 27},{"name": "Claudio Andrés Bravo Muñoz","count": 1},{"name": "Gerard Piqué Bernabéu","count": 8},{"name": "Ivan Rakitić","count": 9},{"name": "Jérémy Mathieu","count": 28},{"name": "Lionel Andrés Messi Cuccittini","count": 3},{"name": "Luis Alberto Suárez Díaz","count": 4},{"name": "Neymar da Silva Santos Junior","count": 38},{"name": "Sergio Busquets i Burgos","count": 18}]},{"name": "Aleix Vidal Parreu","x": 63.75681818181818,"y": 71.24090909090908,"passes": [{"name": "Arda Turan","count": 1},{"name": "Gerard Piqué Bernabéu","count": 31},{"name": "Ivan Rakitić","count": 20},{"name": "Jérémy Mathieu","count": 2},{"name": "Lionel Andrés Messi Cuccittini","count": 16},{"name": "Luis Alberto Suárez Díaz","count": 5},{"name": "Sergio Busquets i Burgos","count": 10}]},{"name": "Arda Turan","x": 71.05166666666668,"y": 24.17,"passes": [{"name": "Claudio Andrés Bravo Muñoz","count": 2},{"name": "Gerard Piqué Bernabéu","count": 6},{"name": "Ivan Rakitić","count": 11},{"name": "Jérémy Mathieu","count": 16},{"name": "Lionel Andrés Messi Cuccittini","count": 7},{"name": "Luis Alberto Suárez Díaz","count": 9},{"name": "Neymar da Silva Santos Junior","count": 25},{"name": "Sergio Busquets i Burgos","count": 11}]},{"name": "Claudio Andrés Bravo Muñoz","x": 11.863157894736842,"y": 38.26842105263158,"passes": [{"name": "Gerard Piqué Bernabéu","count": 12},{"name": "Jérémy Mathieu","count": 8},{"name": "Sergio Busquets i Burgos","count": 5}]},{"name": "Gerard Piqué Bernabéu","x": 52.325287356321844,"y": 59.12758620689656,"passes": [{"name": "Ivan Rakitić","count": 18},{"name": "Jérémy Mathieu","count": 20},{"name": "Lionel Andrés Messi Cuccittini","count": 15},{"name": "Luis Alberto Suárez Díaz","count": 5},{"name": "Neymar da Silva Santos Junior","count": 1},{"name": "Sergio Busquets i Burgos","count": 47}]},{"name": "Ivan Rakitić","x": 70.08813559322033,"y": 50.5728813559322,"passes": [{"name": "Jérémy Mathieu","count": 11},{"name": "Lionel Andrés Messi Cuccittini","count": 24},{"name": "Luis Alberto Suárez Díaz","count": 5},{"name": "Neymar da Silva Santos Junior","count": 6},{"name": "Sergio Busquets i Burgos","count": 22}]},{"name": "Jérémy Mathieu","x": 50.428125,"y": 19.390625,"passes": [{"name": "Lionel Andrés Messi Cuccittini","count": 1},{"name": "Neymar da Silva Santos Junior","count": 9},{"name": "Sergio Busquets i Burgos","count": 26}]},{"name": "Lionel Andrés Messi Cuccittini","x": 80.13703703703703,"y": 52.53333333333334,"passes": [{"name": "Luis Alberto Suárez Díaz","count": 19},{"name": "Neymar da Silva Santos Junior","count": 19},{"name": "Sergio Busquets i Burgos","count": 26}]},{"name": "Luis Alberto Suárez Díaz","x": 79.188,"y": 45.828,"passes": [{"name": "Neymar da Silva Santos Junior","count": 6},{"name": "Sergio Busquets i Burgos","count": 1}]},{"name": "Neymar da Silva Santos Junior","x": 82.33720930232558,"y": 18.067441860465117,"passes": [{"name": "Sergio Busquets i Burgos","count": 6}]}]