[{"name": "Duje Čop","x": 68.125,"y": 23.875,"passes": [{"name": "Federico Ricca Rostagnol","count": 5},{"name": "Francisco Guillermo Ochoa Magaña","count": 2},{"name": "Gonzalo Castro Irizábal","count": 5},{"name": "Ignacio Camacho Barnola","count": 5},{"name": "José Luis García del Pozo","count": 5},{"name": "Juan Pablo Añor Acosta","count": 2},{"name": "Raúl Albentosa Redal","count": 2},{"name": "Roberto José Rosales Altuve","count": 1},{"name": "Roque Luis Santa Cruz Cantero","count": 4},{"name": "Weligton Róbson Pena de Oliveira","count": 1}]},{"name": "Federico Ricca Rostagnol","x": 66.34210526315789,"y": 3.1052631578947367,"passes": [{"name": "Francisco Guillermo Ochoa Magaña","count": 1},{"name": "Gonzalo Castro Irizábal","count": 11},{"name": "Ignacio Camacho Barnola","count": 5},{"name": "José Luis García del Pozo","count": 6},{"name": "Juan Pablo Añor Acosta","count": 1},{"name": "Roque Luis Santa Cruz Cantero","count": 3},{"name": "Weligton Róbson Pena de Oliveira","count": 3}]},{"name": "Francisco Guillermo Ochoa Magaña","x": 9.658333333333333,"y": 39.99166666666667,"passes": [{"name": "Gonzalo Castro Irizábal","count": 1},{"name": "Ignacio Camacho Barnola","count": 1},{"name": "José Luis García del Pozo","count": 1},{"name": "Raúl Albentosa Redal","count": 4},{"name": "Roberto José Rosales Altuve","count": 2},{"name": "Roque Luis Santa Cruz Cantero","count": 1},{"name": "Weligton Róbson Pena de Oliveira","count": 6}]},{"name": "Gonzalo Castro Irizábal","x": 70.1952380952381,"y": 12.890476190476189,"passes": [{"name": "Ignacio Camacho Barnola","count": 6},{"name": "José Luis García del Pozo","count": 12},{"name": "Juan Pablo Añor Acosta","count": 4},{"name": "Roberto José Rosales Altuve","count": 2},{"name": "Roque Luis Santa Cruz Cantero","count": 3}]},{"name": "Ignacio Camacho Barnola","x": 56.388000000000005,"y": 32.512,"passes": [{"name": "José Luis García del Pozo","count": 14},{"name": "Juan Pablo Añor Acosta","count": 5},{"name": "Raúl Albentosa Redal","count": 3},{"name": "Roberto José Rosales Altuve","count": 5},{"name": "Weligton Róbson Pena de Oliveira","count": 2}]},{"name": "José Luis García del Pozo","x": 58.94411764705882,"y": 35.32941176470588,"passes": [{"name": "Juan Pablo Añor Acosta","count": 7},{"name": "Raúl Albentosa Redal","count": 8},{"name": "Roberto José Rosales Altuve","count": 6},{"name": "Roque Luis Santa Cruz Cantero","count": 4},{"name": "Weligton Róbson Pena de Oliveira","count": 4}]},{"name": "Juan Pablo Añor Acosta","x": 70.61333333333333,"y": 54.406666666666666,"passes": [{"name": "Raúl Albentosa Redal","count": 1},{"name": "Roberto José Rosales Altuve","count": 10},{"name": "Roque Luis Santa Cruz Cantero","count": 9},{"name": "Weligton Róbson Pena de Oliveira","count": 1}]},{"name": "Raúl Albentosa Redal","x": 40.268181818181816,"y": 49.64090909090908,"passes": [{"name": "Roberto José Rosales Altuve","count": 7},{"name": "Roque Luis Santa Cruz Cantero","count": 5},{"name": "Weligton Róbson Pena de Oliveira","count": 6}]},{"name": "Roberto José Rosales Altuve","x": 48.190909090909095,"y": 69.62272727272727,"passes": [{"name": "Roque Luis Santa Cruz Cantero","count": 5},{"name": "Weligton Róbson Pena de Oliveira","count": 2}]},{"name": "Roque Luis Santa Cruz Cantero","x": 67.4625,"y": 43.30625,"passes": [{"name": "Weligton Róbson Pena de Oliveira","count": 5}]}]