[{"name": "Abdoul Razzagui Camara","x": 74.38333333333334,"y": 16.166666666666668,"passes": [{"name": "Cheikh N''Doye","count": 3},{"name": "Romain Saïss","count": 1},{"name": "Romain Thomas","count": 1},{"name": "Slimane Sissoko","count": 3},{"name": "Thomas Mangani","count": 4},{"name": "Vincent Manceau","count": 1},{"name": "Yoann Andreu","count": 4}]},{"name": "Cheikh N''Doye","x": 61.79,"y": 49.78,"passes": [{"name": "Ismaël Traoré","count": 4},{"name": "Ludovic Butelle","count": 2},{"name": "Romain Saïss","count": 4},{"name": "Romain Thomas","count": 2},{"name": "Slimane Sissoko","count": 1},{"name": "Thomas Mangani","count": 2},{"name": "Vincent Manceau","count": 7},{"name": "Yoann Andreu","count": 1}]},{"name": "Férébory Doré","x": 72.04285714285714,"y": 33.47142857142857,"passes": [{"name": "Romain Saïss","count": 3},{"name": "Romain Thomas","count": 3},{"name": "Slimane Sissoko","count": 3},{"name": "Thomas Mangani","count": 5},{"name": "Vincent Manceau","count": 2},{"name": "Yoann Andreu","count": 2}]},{"name": "Ismaël Traoré","x": 33.877272727272725,"y": 52.05,"passes": [{"name": "Ludovic Butelle","count": 1},{"name": "Romain Saïss","count": 7},{"name": "Romain Thomas","count": 7},{"name": "Thomas Mangani","count": 14},{"name": "Vincent Manceau","count": 5},{"name": "Yoann Andreu","count": 1}]},{"name": "Ludovic Butelle","x": 10.991666666666667,"y": 42.4,"passes": [{"name": "Romain Saïss","count": 1},{"name": "Romain Thomas","count": 3},{"name": "Slimane Sissoko","count": 4},{"name": "Thomas Mangani","count": 1},{"name": "Vincent Manceau","count": 4},{"name": "Yoann Andreu","count": 1}]},{"name": "Romain Saïss","x": 48.9,"y": 41.791666666666664,"passes": [{"name": "Romain Thomas","count": 5},{"name": "Slimane Sissoko","count": 4},{"name": "Thomas Mangani","count": 7},{"name": "Vincent Manceau","count": 9},{"name": "Yoann Andreu","count": 5}]},{"name": "Romain Thomas","x": 31.47142857142857,"y": 23.8,"passes": [{"name": "Slimane Sissoko","count": 1},{"name": "Thomas Mangani","count": 7},{"name": "Yoann Andreu","count": 9}]},{"name": "Slimane Sissoko","x": 82.27777777777777,"y": 34.21111111111111,"passes": [{"name": "Thomas Mangani","count": 8},{"name": "Vincent Manceau","count": 5},{"name": "Yoann Andreu","count": 5}]},{"name": "Thomas Mangani","x": 61.521875,"y": 38.434375,"passes": [{"name": "Vincent Manceau","count": 7},{"name": "Yoann Andreu","count": 3}]},{"name": "Vincent Manceau","x": 50.95,"y": 73.03636363636363,"passes": []},{"name": "Yoann Andreu","x": 47.752941176470586,"y": 9.876470588235295,"passes": []}]