[{"name": "Alexandre Lacazette","x": 79.53529411764706,"y": 36.252941176470586,"passes": [{"name": "Christophe Jallet","count": 2},{"name": "Clément Grenier","count": 10},{"name": "Corentin Tolisso","count": 8},{"name": "Gnaly Maxwell Cornet","count": 5},{"name": "Jérémy Morel","count": 8},{"name": "Mathieu Valbuena","count": 6},{"name": "Maxime Gonalons","count": 2},{"name": "Samuel Yves Umtiti","count": 3}]},{"name": "Anthony Lopes","x": 10.383333333333333,"y": 38.90555555555555,"passes": [{"name": "Christophe Jallet","count": 1},{"name": "Clément Grenier","count": 1},{"name": "Mapou Yanga-Mbiwa","count": 17},{"name": "Mathieu Valbuena","count": 1},{"name": "Maxime Gonalons","count": 1},{"name": "Samuel Yves Umtiti","count": 8}]},{"name": "Christophe Jallet","x": 67.05,"y": 68.38823529411764,"passes": [{"name": "Clément Grenier","count": 19},{"name": "Corentin Tolisso","count": 3},{"name": "Gnaly Maxwell Cornet","count": 9},{"name": "Mapou Yanga-Mbiwa","count": 14},{"name": "Mathieu Valbuena","count": 1},{"name": "Maxime Gonalons","count": 5},{"name": "Samuel Yves Umtiti","count": 1}]},{"name": "Clément Grenier","x": 69.91891891891892,"y": 49.78648648648648,"passes": [{"name": "Corentin Tolisso","count": 15},{"name": "Gnaly Maxwell Cornet","count": 9},{"name": "Jérémy Morel","count": 2},{"name": "Mapou Yanga-Mbiwa","count": 10},{"name": "Mathieu Valbuena","count": 4},{"name": "Maxime Gonalons","count": 11},{"name": "Samuel Yves Umtiti","count": 3}]},{"name": "Corentin Tolisso","x": 71.27714285714285,"y": 26.62857142857143,"passes": [{"name": "Gnaly Maxwell Cornet","count": 3},{"name": "Jérémy Morel","count": 15},{"name": "Mapou Yanga-Mbiwa","count": 2},{"name": "Mathieu Valbuena","count": 8},{"name": "Maxime Gonalons","count": 10},{"name": "Samuel Yves Umtiti","count": 10}]},{"name": "Gnaly Maxwell Cornet","x": 76.65,"y": 63.910000000000004,"passes": [{"name": "Jérémy Morel","count": 1},{"name": "Mapou Yanga-Mbiwa","count": 3},{"name": "Mathieu Valbuena","count": 2},{"name": "Maxime Gonalons","count": 2}]},{"name": "Jérémy Morel","x": 75.89696969696969,"y": 3.793939393939394,"passes": [{"name": "Mapou Yanga-Mbiwa","count": 1},{"name": "Mathieu Valbuena","count": 18},{"name": "Maxime Gonalons","count": 4},{"name": "Samuel Yves Umtiti","count": 8}]},{"name": "Mapou Yanga-Mbiwa","x": 41.3421052631579,"y": 52.194736842105264,"passes": [{"name": "Mathieu Valbuena","count": 1},{"name": "Maxime Gonalons","count": 6},{"name": "Samuel Yves Umtiti","count": 18}]},{"name": "Mathieu Valbuena","x": 77.2,"y": 17.84,"passes": [{"name": "Maxime Gonalons","count": 5},{"name": "Samuel Yves Umtiti","count": 5}]},{"name": "Maxime Gonalons","x": 60.099999999999994,"y": 41.86451612903225,"passes": [{"name": "Samuel Yves Umtiti","count": 10}]}]