[{"name": "Aaron Ramsey","x": 72.8875,"y": 60.603125,"passes": [{"name": "Alexis Alejandro Sánchez Sánchez","count": 7},{"name": "Francis Joseph Coquelin","count": 11},{"name": "Héctor Bellerín Moruno","count": 22},{"name": "Ignacio Monreal Eraso","count": 2},{"name": "Laurent Koscielny","count": 2},{"name": "Mesut Özil","count": 11},{"name": "Per Mertesacker","count": 4},{"name": "Petr Čech","count": 3},{"name": "Santiago Cazorla González","count": 9},{"name": "Theo Walcott","count": 6}]},{"name": "Alexis Alejandro Sánchez Sánchez","x": 77.4969696969697,"y": 16.248484848484846,"passes": [{"name": "Francis Joseph Coquelin","count": 7},{"name": "Héctor Bellerín Moruno","count": 5},{"name": "Ignacio Monreal Eraso","count": 20},{"name": "Laurent Koscielny","count": 4},{"name": "Mesut Özil","count": 17},{"name": "Per Mertesacker","count": 1},{"name": "Santiago Cazorla González","count": 15},{"name": "Theo Walcott","count": 2}]},{"name": "Francis Joseph Coquelin","x": 59.39069767441861,"y": 41.990697674418605,"passes": [{"name": "Héctor Bellerín Moruno","count": 13},{"name": "Ignacio Monreal Eraso","count": 9},{"name": "Laurent Koscielny","count": 8},{"name": "Mesut Özil","count": 10},{"name": "Per Mertesacker","count": 6},{"name": "Santiago Cazorla González","count": 17},{"name": "Theo Walcott","count": 3}]},{"name": "Héctor Bellerín Moruno","x": 61.86153846153846,"y": 72.52051282051282,"passes": [{"name": "Laurent Koscielny","count": 2},{"name": "Mesut Özil","count": 9},{"name": "Per Mertesacker","count": 18},{"name": "Santiago Cazorla González","count": 13},{"name": "Theo Walcott","count": 2}]},{"name": "Ignacio Monreal Eraso","x": 61.61025641025641,"y": 12.128205128205128,"passes": [{"name": "Laurent Koscielny","count": 11},{"name": "Mesut Özil","count": 7},{"name": "Petr Čech","count": 1},{"name": "Santiago Cazorla González","count": 18}]},{"name": "Laurent Koscielny","x": 40.38648648648648,"y": 31.010810810810813,"passes": [{"name": "Mesut Özil","count": 3},{"name": "Per Mertesacker","count": 18},{"name": "Petr Čech","count": 7},{"name": "Santiago Cazorla González","count": 12}]},{"name": "Mesut Özil","x": 75.15277777777777,"y": 34.88055555555556,"passes": [{"name": "Per Mertesacker","count": 2},{"name": "Petr Čech","count": 2},{"name": "Santiago Cazorla González","count": 12},{"name": "Theo Walcott","count": 1}]},{"name": "Per Mertesacker","x": 37.26756756756757,"y": 57.78108108108108,"passes": [{"name": "Petr Čech","count": 4},{"name": "Santiago Cazorla González","count": 13},{"name": "Theo Walcott","count": 1}]},{"name": "Santiago Cazorla González","x": 60.12542372881356,"y": 35.03898305084746,"passes": [{"name": "Theo Walcott","count": 1}]}]