[{"name": "Brendan Joel Zibusiso Galloway","x": 58.595238095238095,"y": 12.819047619047618,"passes": [{"name": "Gareth Barry","count": 7},{"name": "James McCarthy","count": 4},{"name": "José Ramiro Funes Mori","count": 8},{"name": "Phil Jagielka","count": 4},{"name": "Romelu Lukaku Menama","count": 3},{"name": "Ross Barkley","count": 3},{"name": "Steven Naismith","count": 8}]},{"name": "Gareth Barry","x": 53.410869565217396,"y": 39.619565217391305,"passes": [{"name": "Gerard Deulofeu Lázaro","count": 9},{"name": "Guangtai Jiang","count": 12},{"name": "James McCarthy","count": 7},{"name": "José Ramiro Funes Mori","count": 18},{"name": "Phil Jagielka","count": 15},{"name": "Romelu Lukaku Menama","count": 6},{"name": "Ross Barkley","count": 13},{"name": "Steven Naismith","count": 4},{"name": "Tim Howard","count": 3}]},{"name": "Gerard Deulofeu Lázaro","x": 73.24666666666667,"y": 68.53333333333333,"passes": [{"name": "Guangtai Jiang","count": 9},{"name": "James McCarthy","count": 3},{"name": "José Ramiro Funes Mori","count": 2},{"name": "Phil Jagielka","count": 6},{"name": "Romelu Lukaku Menama","count": 6},{"name": "Ross Barkley","count": 3},{"name": "Steven Naismith","count": 2},{"name": "Tim Howard","count": 2}]},{"name": "Guangtai Jiang","x": 55.9076923076923,"y": 68.98076923076923,"passes": [{"name": "James McCarthy","count": 8},{"name": "José Ramiro Funes Mori","count": 1},{"name": "Phil Jagielka","count": 11},{"name": "Romelu Lukaku Menama","count": 1},{"name": "Ross Barkley","count": 1},{"name": "Steven Naismith","count": 1}]},{"name": "James McCarthy","x": 62.45625,"y": 44.275,"passes": [{"name": "José Ramiro Funes Mori","count": 5},{"name": "Phil Jagielka","count": 12},{"name": "Romelu Lukaku Menama","count": 4},{"name": "Ross Barkley","count": 12},{"name": "Steven Naismith","count": 7},{"name": "Tim Howard","count": 2}]},{"name": "José Ramiro Funes Mori","x": 43.800000000000004,"y": 20.513953488372092,"passes": [{"name": "Phil Jagielka","count": 19},{"name": "Ross Barkley","count": 10},{"name": "Steven Naismith","count": 6},{"name": "Tim Howard","count": 15}]},{"name": "Phil Jagielka","x": 47.92558139534884,"y": 53.3093023255814,"passes": [{"name": "Romelu Lukaku Menama","count": 2},{"name": "Ross Barkley","count": 4},{"name": "Tim Howard","count": 6}]},{"name": "Romelu Lukaku Menama","x": 71.71875,"y": 39.79375,"passes": [{"name": "Ross Barkley","count": 11},{"name": "Steven Naismith","count": 3}]},{"name": "Ross Barkley","x": 72.6,"y": 30.816129032258065,"passes": [{"name": "Steven Naismith","count": 11}]}]